osam/__init__.py
osam/main.py
osam/tasks.py
osam/utils/__init__.py
osam/utils/cloud_provider_api_handler.py
osam/utils/keycloak_handler.py
osam/utils/tools.py
rs_osam-0.2.dist-info/METADATA
rs_osam-0.2.dist-info/WHEEL
rs_osam-0.2.dist-info/RECORD
