Metadata-Version: 2.3
Name: rs-osam
Version: 0.2
Summary: Copernicus Sentinel OSAM (Object Storage Access Manager).
License: Apache-2.0
Keywords: copernicus,sentinel,processing
Author: ESA under contract with Airbus and CS
Author-email: ops_coprs@airbus.com
Requires-Python: >=3.11,<4.0
Classifier: Development Status :: 3 - Alpha
Classifier: Framework :: FastAPI
Classifier: Framework :: OpenTelemetry
Classifier: Intended Audience :: Developers
Classifier: Intended Audience :: Science/Research
Classifier: License :: OSI Approved :: Apache Software License
Classifier: Programming Language :: Python :: 3
Classifier: Programming Language :: Python :: 3.11
Classifier: Programming Language :: Python :: 3.12
Classifier: Programming Language :: Python :: 3.13
Classifier: Topic :: Scientific/Engineering :: GIS
Classifier: Topic :: Scientific/Engineering :: Image Processing
Requires-Dist: jsonpatch (>=1.33,<2.0)
Requires-Dist: openapi-core (>=0.19.5,<0.20.0)
Requires-Dist: ovh (>=1.2.0,<2.0.0)
Requires-Dist: rs-server-common
